palantir/__init__.py
palantir/spark/__init__.py
palantir/spark/time/__init__.py
palantir/spark/time/offset_date_time_udt.py
palantir.spark.time-0.2.3.dist-info/DESCRIPTION.rst
palantir.spark.time-0.2.3.dist-info/METADATA
palantir.spark.time-0.2.3.dist-info/RECORD
palantir.spark.time-0.2.3.dist-info/WHEEL
palantir.spark.time-0.2.3.dist-info/metadata.json
palantir.spark.time-0.2.3.dist-info/top_level.txt
