Metadata-Version: 2.0
Name: palantir.spark.time
Version: 0.2.3
Summary: UNKNOWN
Home-page: UNKNOWN
Author: UNKNOWN
Author-email: UNKNOWN
License: Apache License 2.0
Platform: UNKNOWN
Classifier: License :: OSI Approved :: Apache Software License
Requires-Dist: py4j (>=0.9)
Requires-Dist: pytz
Provides-Extra: test
Requires-Dist: pytest; extra == 'test'
